tilda/__init__.py
tilda/base.py
tilda/client.py
tilda/error.py
tilda/page.py
tilda/project.py
tilda_api-0.2.1.dist-info/DESCRIPTION.rst
tilda_api-0.2.1.dist-info/METADATA
tilda_api-0.2.1.dist-info/RECORD
tilda_api-0.2.1.dist-info/WHEEL
tilda_api-0.2.1.dist-info/metadata.json
tilda_api-0.2.1.dist-info/top_level.txt
