Metadata-Version: 2.0
Name: tilda-api
Version: 0.2.1
Summary: A python implementation of the Tilda.cc API
Home-page: https://github.com/dotzero/tilda-api-python
Author: dotzero
Author-email: mail@dotzero.ru
License: MIT
Platform: UNKNOWN
